gollum/__init__.py
gollum/coolTLUSTY.py
gollum/experimental.py
gollum/phoenix.py
gollum/precomputed_spectrum.py
gollum/sonora.py
gollum/telluric.py
gollum/utilities.py
gollum-0.4.1.dist-info/LICENSE
gollum-0.4.1.dist-info/METADATA
gollum-0.4.1.dist-info/WHEEL
gollum-0.4.1.dist-info/top_level.txt
gollum-0.4.1.dist-info/RECORD
