Metadata-Version: 2.1
Name: gollum
Version: 0.4.1
Summary: An intuitive programmatic and visual interface for precomputed synthetic spectral model grids
Home-page: https://github.com/BrownDwarf/gollum
Author: gully
Author-email: Sujay Shankar <sujays2001@gmail.com>, Michael Gully-Santiago <igully@gmail.com>, Caroline Morley <cmorley@utexas.edu>, Jiayi Cao <jiayicao@utexas.edu>
Maintainer-email: Sujay Shankar <sujays2001@gmail.com>
License: MIT License
Project-URL: Homepage, https://github.com/BrownDwarf/gollum
Project-URL: Issues, https://github.com/BrownDwarf/gollum/issues
Classifier: Programming Language :: Python :: 3
Classifier: License :: OSI Approved :: MIT License
Classifier: Operating System :: OS Independent
Requires-Python: >=3.8
License-File: LICENSE
Requires-Dist: numpy
Requires-Dist: scipy
Requires-Dist: matplotlib
Requires-Dist: astropy
Requires-Dist: specutils
Requires-Dist: tqdm
Requires-Dist: pandas
Requires-Dist: bokeh
Requires-Dist: python-dotenv
